arxiv_scan/__init__.py
arxiv_scan/__main__.py
arxiv_scan/_version.py
arxiv_scan/categories.py
arxiv_scan/config.py
arxiv_scan/entry_evaluation.py
arxiv_scan/oai_api.py
arxiv_scan/output.py
arxiv_scan/parse.py
arxiv_scan/wordcounter.py
arxiv_scan-1.2.dist-info/licenses/LICENSE
arxiv_scan-1.2.dist-info/METADATA
arxiv_scan-1.2.dist-info/WHEEL
arxiv_scan-1.2.dist-info/entry_points.txt
arxiv_scan-1.2.dist-info/top_level.txt
arxiv_scan-1.2.dist-info/RECORD
