Metadata-Version: 2.4
Name: arxiv-scan
Version: 1.2
Summary: Find preprints relevant to your individual research
Home-page: https://github.com/matiscke/arxiv-scan
Author: Martin Schlecker
Author-email: schlecker@mpia.de
Maintainer: Simeon Doetsch
Maintainer-email: mail@simske.com
Project-URL: Bug Tracker, https://github.com/matiscke/arxiv-scan/issues
Classifier: Programming Language :: Python :: 3
Classifier: Operating System :: OS Independent
Classifier: Environment :: Console
Classifier: Topic :: Scientific/Engineering :: Astronomy
Classifier: Topic :: Scientific/Engineering :: Physics
Classifier: License :: OSI Approved :: MIT License
Requires-Python: >=3.5
License-File: LICENSE
Requires-Dist: termcolor
Requires-Dist: pytz
Dynamic: license-file
